teval/__init__.py
teval/metrics.py
teval-0.1.2.dist-info/licenses/LICENSE
teval-0.1.2.dist-info/METADATA
teval-0.1.2.dist-info/WHEEL
teval-0.1.2.dist-info/top_level.txt
teval-0.1.2.dist-info/RECORD
