Metadata-Version: 2.4
Name: teval
Version: 0.1.2
Summary: Trivial LLM eval - as simple as possible
Author: tvaroska
License: Apache-2.0
Project-URL: Homepage, https://github.com/tvaroska/teval
Project-URL: Bug Tracker, https://github.com/tvaroska/teval/issues
Project-URL: Repository, https://github.com/tvaroska/teval
Project-URL: Documentation, https://github.com/tvaroska/teval/tree/main/docs
Project-URL: Changelog, https://github.com/tvaroska/teval/blob/main/CHANGELOG.md
Keywords: llm,evaluation,metrics,testing,ai
Classifier: Development Status :: 3 - Alpha
Classifier: Intended Audience :: Developers
Classifier: License :: OSI Approved :: Apache Software License
Classifier: Programming Language :: Python :: 3
Classifier: Programming Language :: Python :: 3.10
Classifier: Programming Language :: Python :: 3.11
Classifier: Programming Language :: Python :: 3.12
Classifier: Programming Language :: Python :: 3.13
Classifier: Topic :: Software Development :: Libraries :: Python Modules
Classifier: Topic :: Software Development :: Testing
Classifier: Topic :: Scientific/Engineering :: Artificial Intelligence
Requires-Python: <3.14,>=3.10
License-File: LICENSE
Requires-Dist: pydantic<3.0.0,>=2.9.0
Dynamic: license-file
